datahub/__init__.py
datahub/__main__.py
datahub/entrypoints.py
datahub/py.typed
datahub/cli/__init__.py
datahub/cli/check_cli.py
datahub/cli/cli_utils.py
datahub/cli/delete_cli.py
datahub/cli/docker.py
datahub/cli/docker_check.py
datahub/cli/get_cli.py
datahub/cli/ingest_cli.py
datahub/cli/json_file.py
datahub/cli/migrate.py
datahub/cli/migration_utils.py
datahub/cli/put_cli.py
datahub/cli/telemetry.py
datahub/configuration/__init__.py
datahub/configuration/common.py
datahub/configuration/config_loader.py
datahub/configuration/github.py
datahub/configuration/import_resolver.py
datahub/configuration/kafka.py
datahub/configuration/source_common.py
datahub/configuration/time_window_config.py
datahub/configuration/toml.py
datahub/configuration/yaml.py
datahub/emitter/__init__.py
datahub/emitter/kafka_emitter.py
datahub/emitter/mce_builder.py
datahub/emitter/mcp.py
datahub/emitter/mcp_builder.py
datahub/emitter/rest_emitter.py
datahub/emitter/serialization_helper.py
datahub/ingestion/__init__.py
datahub/ingestion/api/__init__.py
datahub/ingestion/api/closeable.py
datahub/ingestion/api/committable.py
datahub/ingestion/api/common.py
datahub/ingestion/api/ingestion_job_checkpointing_provider_base.py
datahub/ingestion/api/ingestion_job_reporting_provider_base.py
datahub/ingestion/api/ingestion_job_state_provider.py
datahub/ingestion/api/ingestion_state_provider.py
datahub/ingestion/api/registry.py
datahub/ingestion/api/report.py
datahub/ingestion/api/sink.py
datahub/ingestion/api/source.py
datahub/ingestion/api/transform.py
datahub/ingestion/api/workunit.py
datahub/ingestion/extractor/__init__.py
datahub/ingestion/extractor/extractor_registry.py
datahub/ingestion/extractor/mce_extractor.py
datahub/ingestion/extractor/schema_util.py
datahub/ingestion/graph/__init__.py
datahub/ingestion/graph/client.py
datahub/ingestion/reporting/__init__.py
datahub/ingestion/reporting/datahub_ingestion_reporting_provider.py
datahub/ingestion/reporting/reporting_provider_registry.py
pingpong_datahub-0.8.26.dist-info/METADATA
pingpong_datahub-0.8.26.dist-info/WHEEL
pingpong_datahub-0.8.26.dist-info/entry_points.txt
pingpong_datahub-0.8.26.dist-info/top_level.txt
pingpong_datahub-0.8.26.dist-info/RECORD
